capt_archive_converter/__init__.py
capt_archive_converter/__main__.py
capt_archive_converter/main/__init__.py
capt_archive_converter/processors/__init__.py
capt_archive_converter/processors/arc_conv_cb_proc.py
capt_archive_converter/processors/arc_conv_pdf_proc.py
capt_archive_converter/processors/arc_convert_worker.py
capt_archive_converter/utils/__init__.py
capt_archive_converter/utils/arc_conv_helpers.py
capt_archive_converter/utils/arc_convert_util.py
capt_archive_converter/utils/logger.py
capt_archive_converter/widgets/__init__.py
capt_archive_converter/widgets/file_mgnt.py
capt_archive_converter/widgets/prgrs_wdgt.py
capt_archive_converter-1.0.0.dist-info/licenses/LICENCE
capt_archive_converter-1.0.0.dist-info/METADATA
capt_archive_converter-1.0.0.dist-info/WHEEL
capt_archive_converter-1.0.0.dist-info/entry_points.txt
capt_archive_converter-1.0.0.dist-info/top_level.txt
capt_archive_converter-1.0.0.dist-info/RECORD
