Metadata-Version: 2.4
Name: capt-archive-converter
Version: 1.0.0
Summary: Part of a Comic Archive Processing Toolkit, Archive Converter for CBR, CBZ, and PDF files
Author-email: Tezdread <quixlinedesign@gmail.com>
License: GPL-3.0-or-later
Project-URL: Homepage, https://github.com/quixline/capt_archive_converter
Project-URL: Repository, https://github.com/quixline/capt_archive_converter
Project-URL: Issues, https://github.com/quixline/capt_archive_converter/issues
Classifier: Programming Language :: Python :: 3
Classifier: License :: OSI Approved :: GNU General Public License v3 (GPLv3)
Classifier: Operating System :: OS Independent
Requires-Python: >=3.8
License-File: LICENCE
Requires-Dist: PyQt6
Requires-Dist: rarfile
Requires-Dist: PyMuPDF
Requires-Dist: Pillow
Dynamic: license-file
